calcyoulater/__init__.py
calcyoulater/unit_tests.py
calcyoulater/static/img/calcyoulater.PNG
calcyoulater/static/styles/style.css
calcyoulater/templates/add.html
calcyoulater/templates/divide.html
calcyoulater/templates/index.html
calcyoulater/templates/multiply.html
calcyoulater/templates/subtract.html
calcyoulater-0.0.1.dist-info/METADATA
calcyoulater-0.0.1.dist-info/WHEEL
calcyoulater-0.0.1.dist-info/top_level.txt
calcyoulater-0.0.1.dist-info/RECORD
